{
  "_comment": "Supplement to seed-categories.js CATEGORIES map. Built 2026-07-16 from Josh's other-Mac library-cache.json (575 uncategorized products across 60 developers). dev -> product name -> {category, subcategory}. Merged (not overwritten) into the registry by seed-categories.js. MIDI uses subcategory null; Application uses 'Application'.",
  "- Minimal Audio": {
    "Rift": { "category": "Effect", "subcategory": "Distortion" }
  },
  "AIR Music Tech": {
    "AIREnhancer": { "category": "Effect", "subcategory": "Distortion" },
    "AIRFrequencyShifter": { "category": "Effect", "subcategory": "Modulation" },
    "Boom": { "category": "Instrument", "subcategory": "Drums" },
    "DB-33": { "category": "Instrument", "subcategory": "Keys" },
    "MiniGrand": { "category": "Instrument", "subcategory": "Keys" },
    "Structure": { "category": "Instrument", "subcategory": "Sampler" },
    "Vacuum": { "category": "Instrument", "subcategory": "Synth" }
  },
  "Acon AS": {
    "Acon Digital Verberate Immersive 2": { "category": "Effect", "subcategory": "Reverb" },
    "VerberateImmersive2": { "category": "Effect", "subcategory": "Reverb" }
  },
  "Acon Digital": {
    "Acoustica": { "category": "Effect", "subcategory": "Utility" },
    "AcousticaARA": { "category": "Effect", "subcategory": "Utility" },
    "Convolve": { "category": "Effect", "subcategory": "Reverb" },
    "DeBird": { "category": "Effect", "subcategory": "Utility" },
    "DeBuzz": { "category": "Effect", "subcategory": "Utility" },
    "DeBuzz Dialogue": { "category": "Effect", "subcategory": "Utility" },
    "DeClick Dialogue": { "category": "Effect", "subcategory": "Utility" },
    "DeClickDialogue": { "category": "Effect", "subcategory": "Utility" },
    "DePlosive": { "category": "Effect", "subcategory": "Utility" },
    "DePlosive Dialogue": { "category": "Effect", "subcategory": "Utility" },
    "DeRustle": { "category": "Effect", "subcategory": "Utility" },
    "DeRustle Dialogue": { "category": "Effect", "subcategory": "Utility" },
    "DeWind": { "category": "Effect", "subcategory": "Utility" },
    "DeWind Dialogue": { "category": "Effect", "subcategory": "Utility" },
    "Dither": { "category": "Effect", "subcategory": "Utility" },
    "Dynamics": { "category": "Effect", "subcategory": "Dynamics" },
    "Extract Dialogue": { "category": "Effect", "subcategory": "Utility" },
    "ExtractDialogue": { "category": "Effect", "subcategory": "Utility" },
    "Limit": { "category": "Effect", "subcategory": "Dynamics" },
    "Remix": { "category": "Effect", "subcategory": "Utility" },
    "Transfer": { "category": "Effect", "subcategory": "Utility" }
  },
  "Acon Digital AS": {
    "Acon Digital DeClick 2": { "category": "Effect", "subcategory": "Utility" },
    "Acon Digital DeClip 2": { "category": "Effect", "subcategory": "Utility" },
    "Acon Digital DeHum 2": { "category": "Effect", "subcategory": "Utility" },
    "Acon Digital DeNoise 2": { "category": "Effect", "subcategory": "Utility" },
    "Acon Digital Verberate 2": { "category": "Effect", "subcategory": "Reverb" },
    "Acon Digital Vitalize": { "category": "Effect", "subcategory": "Distortion" },
    "DeClick2": { "category": "Effect", "subcategory": "Utility" },
    "DeClip2": { "category": "Effect", "subcategory": "Utility" },
    "DeHum2": { "category": "Effect", "subcategory": "Utility" },
    "DeNoise2": { "category": "Effect", "subcategory": "Utility" },
    "Verberate2": { "category": "Effect", "subcategory": "Reverb" },
    "Vitalize": { "category": "Effect", "subcategory": "Distortion" }
  },
  "Antares": {
    "Aspire": { "category": "Effect", "subcategory": "Pitch" },
    "AVOX ASPIRE": { "category": "Effect", "subcategory": "Pitch" },
    "AVOX CHOIR": { "category": "Effect", "subcategory": "Pitch" },
    "AVOX PUNCH": { "category": "Effect", "subcategory": "Dynamics" },
    "AVOX THROAT": { "category": "Effect", "subcategory": "Pitch" },
    "AVOX WARM": { "category": "Effect", "subcategory": "Distortion" },
    "Choir": { "category": "Effect", "subcategory": "Pitch" },
    "Harmony Engine": { "category": "Effect", "subcategory": "Pitch" },
    "Harmony Engine 4x": { "category": "Effect", "subcategory": "Pitch" },
    "Punch": { "category": "Effect", "subcategory": "Dynamics" },
    "Throat": { "category": "Effect", "subcategory": "Pitch" },
    "Warm": { "category": "Effect", "subcategory": "Distortion" }
  },
  "Applied Acoustics Systems": {
    "Ultra Analog Session 2": { "category": "Instrument", "subcategory": "Synth" }
  },
  "Arturia": {
    "Dist OPAMP-21": { "category": "Effect", "subcategory": "Distortion" },
    "Dist TUBE-CULTURE": { "category": "Effect", "subcategory": "Distortion" }
  },
  "Audiomodern": {
    "Riffer": { "category": "MIDI", "subcategory": null }
  },
  "Avid": {
    "304C": { "category": "Effect", "subcategory": "Dynamics" },
    "304E": { "category": "Effect", "subcategory": "EQ" },
    "BF-2A": { "category": "Effect", "subcategory": "Dynamics" },
    "BF-3A": { "category": "Effect", "subcategory": "Dynamics" },
    "Black Shiny Wah": { "category": "Effect", "subcategory": "EQ" },
    "Fairchild660": { "category": "Effect", "subcategory": "Dynamics" },
    "Fairchild670": { "category": "Effect", "subcategory": "Dynamics" },
    "Focusrite d2": { "category": "Effect", "subcategory": "EQ" },
    "Focusrite d3": { "category": "Effect", "subcategory": "Dynamics" },
    "GrooveCell": { "category": "Instrument", "subcategory": "Drums" },
    "Impact": { "category": "Effect", "subcategory": "Dynamics" },
    "moogerfooger AD": { "category": "Effect", "subcategory": "Delay" },
    "moogerfooger LP": { "category": "Effect", "subcategory": "EQ" },
    "moogerfooger Ph": { "category": "Effect", "subcategory": "Modulation" },
    "moogerfooger RM": { "category": "Effect", "subcategory": "Modulation" },
    "PlayCell": { "category": "Instrument", "subcategory": "Sampler" },
    "ProSubharmonic": { "category": "Effect", "subcategory": "Utility" },
    "Purple Audio MC77": { "category": "Effect", "subcategory": "Dynamics" },
    "ReVibeII": { "category": "Effect", "subcategory": "Reverb" },
    "Roto Speaker": { "category": "Effect", "subcategory": "Modulation" },
    "Smack": { "category": "Effect", "subcategory": "Dynamics" },
    "White Boost": { "category": "Effect", "subcategory": "Distortion" }
  },
  "Baby Audio": {
    "Transit 2": { "category": "Effect", "subcategory": "Creative" }
  },
  "Blue Cat Audio": {
    "BC Freeceiver": { "category": "Effect", "subcategory": "Utility" }
  },
  "Cableguys": {
    "Kickstart 2": { "category": "Effect", "subcategory": "Modulation" },
    "ShaperBox 3": { "category": "Effect", "subcategory": "Multi-Effect" }
  },
  "Celemony": {
    "Tonalic": { "category": "Instrument", "subcategory": "Sampler" }
  },
  "Cradle": {
    "Orion": { "category": "Effect", "subcategory": "Multi-Effect" },
    "The God Particle": { "category": "Effect", "subcategory": "Multi-Effect" },
    "The Spirit": { "category": "Effect", "subcategory": "Multi-Effect" },
    "TheSpirit": { "category": "Effect", "subcategory": "Multi-Effect" }
  },
  "Cytomic": {
    "The Scream": { "category": "Effect", "subcategory": "Distortion" }
  },
  "EaReckon": {
    "MIDIPolysher": { "category": "MIDI", "subcategory": null }
  },
  "Embody": {
    "Immerse Studio Signature Edition": { "category": "Effect", "subcategory": "Utility" },
    "Immerse Virtual Studio": { "category": "Effect", "subcategory": "Utility" },
    "Immerse Virtual Studio Signature Edition": { "category": "Effect", "subcategory": "Utility" }
  },
  "GumCuisine": {
    "GumCuisineKick": { "category": "Instrument", "subcategory": "Drums" }
  },
  "JMG Sound": {
    "Cryostasis": { "category": "Effect", "subcategory": "Reverb" }
  },
  "Joseph Lyncheski": {
    "MiniMeters": { "category": "Effect", "subcategory": "Utility" }
  },
  "Josephlyncheski": {
    "MiniMeters": { "category": "Effect", "subcategory": "Utility" }
  },
  "Kilohearts": {
    "kHs Channel Mixer": { "category": "Effect", "subcategory": "Utility" },
    "kHs Clipper": { "category": "Effect", "subcategory": "Distortion" },
    "kHs Compactor": { "category": "Effect", "subcategory": "Dynamics" },
    "kHs Convolver": { "category": "Effect", "subcategory": "Reverb" },
    "kHs Frequency Shifter": { "category": "Effect", "subcategory": "Modulation" },
    "kHs Haas": { "category": "Effect", "subcategory": "Imaging" },
    "kHs Pitch Shifter": { "category": "Effect", "subcategory": "Pitch" },
    "kHs Resonator": { "category": "Effect", "subcategory": "Modulation" },
    "kHs Reverser": { "category": "Effect", "subcategory": "Creative" },
    "kHs Shaper": { "category": "Effect", "subcategory": "Distortion" },
    "kHs Tape Stop": { "category": "Effect", "subcategory": "Creative" }
  },
  "MeldaProduction": {
    "MBitFunMB": { "category": "Effect", "subcategory": "Distortion" },
    "MCabinetMB": { "category": "Effect", "subcategory": "Distortion" },
    "MCCGenerator": { "category": "MIDI", "subcategory": null },
    "MCenter": { "category": "Effect", "subcategory": "Imaging" },
    "MCombMB": { "category": "Effect", "subcategory": "Modulation" },
    "MDoubleTrackerMB": { "category": "Effect", "subcategory": "Modulation" },
    "MDynamicsMB": { "category": "Effect", "subcategory": "Dynamics" },
    "MDynamicsMBLarge": { "category": "Effect", "subcategory": "Dynamics" },
    "MFreqShifterMB": { "category": "Effect", "subcategory": "Modulation" },
    "MMatcher": { "category": "Effect", "subcategory": "EQ" },
    "MRatioMB": { "category": "Effect", "subcategory": "Dynamics" },
    "MRhythmizerMB": { "category": "Effect", "subcategory": "Creative" },
    "MSpectralDynamicsMini": { "category": "Effect", "subcategory": "Dynamics" },
    "MSuperLooper16in16out": { "category": "Effect", "subcategory": "Utility" },
    "MSuperLooper16out": { "category": "Effect", "subcategory": "Utility" },
    "MWaveFolderMB": { "category": "Effect", "subcategory": "Distortion" },
    "MWobblerMB": { "category": "Effect", "subcategory": "Modulation" },
    "MXXX1": { "category": "Effect", "subcategory": "Multi-Effect" },
    "MXXX6in6out": { "category": "Effect", "subcategory": "Multi-Effect" },
    "MXXX6out": { "category": "Effect", "subcategory": "Multi-Effect" }
  },
  "MicroMusic": {
    "MicroMusic": { "category": "Effect", "subcategory": "Utility" }
  },
  "Modalics": {
    "Beat Scholar MIDI": { "category": "MIDI", "subcategory": null },
    "BitFuzzer": { "category": "Effect", "subcategory": "Distortion" },
    "EON-Arp MIDI": { "category": "MIDI", "subcategory": null }
  },
  "Native Instruments": {
    "Guitar Rig 7": { "category": "Effect", "subcategory": "Multi-Effect" },
    "Reaktor 6 FX": { "category": "Effect", "subcategory": "Multi-Effect" },
    "Replika XT": { "category": "Effect", "subcategory": "Delay" },
    "Supercharger GT": { "category": "Effect", "subcategory": "Dynamics" }
  },
  "New Sonic Arts": {
    "Freestyle": { "category": "Instrument", "subcategory": "Synth" }
  },
  "Newfangled Audio": {
    "Newfangled EQuivocate": { "category": "Effect", "subcategory": "EQ" }
  },
  "OKAYAudio": {
    "Swole": { "category": "Effect", "subcategory": "Multi-Effect" }
  },
  "Pitch Innovations": {
    "Groove Shaper LITE": { "category": "MIDI", "subcategory": null }
  },
  "Plugin Alliance": {
    "Bridge": { "category": "Application", "subcategory": "Application" },
    "bx_cleansweep Pro": { "category": "Effect", "subcategory": "EQ" },
    "bx_console Focusrite SC": { "category": "Effect", "subcategory": "Multi-Effect" },
    "bx_console N": { "category": "Effect", "subcategory": "Multi-Effect" },
    "bx_control V2": { "category": "Effect", "subcategory": "Utility" },
    "bx_crispyscale": { "category": "Effect", "subcategory": "Pitch" },
    "bx_crispytuner": { "category": "Effect", "subcategory": "Pitch" },
    "bx_delay2500": { "category": "Effect", "subcategory": "Delay" },
    "bx_digital V3": { "category": "Effect", "subcategory": "EQ" },
    "bx_hybrid V2": { "category": "Effect", "subcategory": "EQ" },
    "bx_rockergain100": { "category": "Effect", "subcategory": "Distortion" },
    "bx_rockrack V3": { "category": "Effect", "subcategory": "Distortion" },
    "bx_saturator V2": { "category": "Effect", "subcategory": "Distortion" },
    "bx_XL V2": { "category": "Effect", "subcategory": "Dynamics" },
    "Cut Classic High Flyer": { "category": "Effect", "subcategory": "EQ" },
    "elysia karacter master": { "category": "Effect", "subcategory": "Distortion" },
    "elysia museq Master": { "category": "Effect", "subcategory": "EQ" },
    "ENGL E646 VS": { "category": "Effect", "subcategory": "Distortion" },
    "ENGL E765 RT": { "category": "Effect", "subcategory": "Distortion" },
    "ENGL Savage 120": { "category": "Effect", "subcategory": "Distortion" },
    "Fuchs Train II": { "category": "Effect", "subcategory": "Distortion" },
    "INSTRUMENT": { "category": "Application", "subcategory": "Application" },
    "Maag MAGNUM-K": { "category": "Effect", "subcategory": "Dynamics" },
    "Millennia NSEQ-2": { "category": "Effect", "subcategory": "EQ" },
    "Millennia TCL-2": { "category": "Effect", "subcategory": "Dynamics" },
    "Pro Audio DSP DSM V3": { "category": "Effect", "subcategory": "Dynamics" },
    "Sounds Listener": { "category": "Application", "subcategory": "Application" },
    "Sounds": { "category": "Application", "subcategory": "Application" },
    "SPL Attacker Plus": { "category": "Effect", "subcategory": "Dynamics" },
    "SpliceBridge": { "category": "Application", "subcategory": "Application" },
    "Splice": { "category": "Application", "subcategory": "Application" },
    "Vertigo VSC-2": { "category": "Effect", "subcategory": "Dynamics" },
    "Vertigo VSM-3": { "category": "Effect", "subcategory": "Distortion" }
  },
  "Polyverse": {
    "Filterverse": { "category": "Effect", "subcategory": "EQ" }
  },
  "PreSonus": {
    "AAX Shell": { "category": "Application", "subcategory": "Application" },
    "VST3 Shell": { "category": "Application", "subcategory": "Application" }
  },
  "Propellerhead Software AB": {
    "Reason Rack Plugin": { "category": "Instrument", "subcategory": "Synth" }
  },
  "Sennheiser / Dear Reality": {
    "dearVR pro": { "category": "Effect", "subcategory": "Utility" }
  },
  "Serato Audio Research": {
    "Serato Sample": { "category": "Instrument", "subcategory": "Sampler" }
  },
  "Sessionwire": {
    "Receive": { "category": "Effect", "subcategory": "Utility" },
    "Send": { "category": "Effect", "subcategory": "Utility" },
    "Talkback": { "category": "Effect", "subcategory": "Utility" },
    "Talkback Receive": { "category": "Effect", "subcategory": "Utility" },
    "Talkback Send": { "category": "Effect", "subcategory": "Utility" }
  },
  "Softube": {
    "American Mainstayer": { "category": "Effect", "subcategory": "Distortion" },
    "Bass Standard Line V8": { "category": "Effect", "subcategory": "Distortion" },
    "Custom 100W": { "category": "Effect", "subcategory": "Distortion" },
    "Top Boost": { "category": "Effect", "subcategory": "Distortion" },
    "Empirical Labs Prof Punch-Knuckles": { "category": "Effect", "subcategory": "Distortion" },
    "Acoustic Feedback": { "category": "Effect", "subcategory": "Creative" },
    "American Class A": { "category": "Effect", "subcategory": "Multi-Effect" },
    "Amplifiers": { "category": "Effect", "subcategory": "Distortion" },
    "Atlantis Dual Chambers": { "category": "Effect", "subcategory": "Modulation" },
    "Bad Speaker": { "category": "Effect", "subcategory": "Distortion" },
    "Blaze Works Amplification": { "category": "Effect", "subcategory": "Distortion" },
    "British Class A Drive": { "category": "Effect", "subcategory": "Distortion" },
    "British Class A": { "category": "Effect", "subcategory": "Multi-Effect" },
    "Bus Processor": { "category": "Effect", "subcategory": "Dynamics" },
    "Chandler Limited Curve Bender": { "category": "Effect", "subcategory": "EQ" },
    "Clipper": { "category": "Effect", "subcategory": "Distortion" },
    "Dimensions": { "category": "Effect", "subcategory": "Modulation" },
    "Dirty Tape": { "category": "Effect", "subcategory": "Distortion" },
    "Doom Chvrch": { "category": "Effect", "subcategory": "Reverb" },
    "Drawmer 1973": { "category": "Effect", "subcategory": "Dynamics" },
    "Echoes": { "category": "Effect", "subcategory": "Delay" },
    "Equalizers": { "category": "Effect", "subcategory": "EQ" },
    "Fix Doubler": { "category": "Effect", "subcategory": "Modulation" },
    "Flow Mastering Suite": { "category": "Effect", "subcategory": "Multi-Effect" },
    "Flow Mixing Suite": { "category": "Effect", "subcategory": "Multi-Effect" },
    "Layers": { "category": "Instrument", "subcategory": "Sampler" },
    "Overstayer M-A-S Extended": { "category": "Effect", "subcategory": "Distortion" },
    "Overstayer M-A-S": { "category": "Effect", "subcategory": "Distortion" },
    "Summit Audio EQF-100": { "category": "Effect", "subcategory": "EQ" },
    "Summit Audio Grand Channel": { "category": "Effect", "subcategory": "Multi-Effect" },
    "Summit Audio TLA-100A": { "category": "Effect", "subcategory": "Dynamics" },
    "Tape Echoes": { "category": "Effect", "subcategory": "Delay" },
    "Tape Multi Track": { "category": "Effect", "subcategory": "Distortion" },
    "Tape": { "category": "Effect", "subcategory": "Distortion" },
    "Trident A-Range": { "category": "Effect", "subcategory": "EQ" },
    "Tube-Tech Blue Tone": { "category": "Effect", "subcategory": "Multi-Effect" },
    "Tube-Tech CL 1B mk II": { "category": "Effect", "subcategory": "Dynamics" },
    "Tube-Tech Classic Channel mk II": { "category": "Effect", "subcategory": "Multi-Effect" },
    "Tube-Tech Equalizers mk II": { "category": "Effect", "subcategory": "EQ" },
    "Tube-Tech SMC 2B": { "category": "Effect", "subcategory": "Dynamics" },
    "Valley People Dyna-mite Slam": { "category": "Effect", "subcategory": "Dynamics" },
    "Valley People Dyna-mite": { "category": "Effect", "subcategory": "Dynamics" },
    "Vocal Tuner": { "category": "Effect", "subcategory": "Pitch" },
    "Weiss DS1-MK3": { "category": "Effect", "subcategory": "Dynamics" },
    "Weiss EQ1": { "category": "Effect", "subcategory": "EQ" },
    "Widener": { "category": "Effect", "subcategory": "Imaging" }
  },
  "Sonarworks": {
    "SoundID VoiceAI": { "category": "Effect", "subcategory": "Utility" },
    "SoundIDVoiceAI": { "category": "Effect", "subcategory": "Utility" }
  },
  "Sonnox": {
    "Soften": { "category": "Effect", "subcategory": "EQ" }
  },
  "Sound Device Digital": {
    "Autoformer": { "category": "Effect", "subcategory": "Distortion" },
    "Verbum": { "category": "Effect", "subcategory": "Reverb" }
  },
  "SoundRadix": {
    "Auto-Align 2": { "category": "Effect", "subcategory": "Utility" },
    "AutoAlign2": { "category": "Effect", "subcategory": "Utility" },
    "Pi": { "category": "Effect", "subcategory": "Utility" },
    "POWAIR": { "category": "Effect", "subcategory": "Dynamics" }
  },
  "Thehim": {
    "Sub Ninja": { "category": "Effect", "subcategory": "Utility" }
  },
  "Tokyo Dawn Labs": {
    "TDR Molotok": { "category": "Effect", "subcategory": "Dynamics" }
  },
  "UJAM": {
    "BM-GLORY": { "category": "Instrument", "subcategory": "Drums" }
  },
  "UVI": {
    "DrumReplacer": { "category": "Effect", "subcategory": "Utility" },
    "Opal": { "category": "Instrument", "subcategory": "Synth" },
    "Phasor": { "category": "Effect", "subcategory": "Modulation" },
    "Relayer": { "category": "Effect", "subcategory": "Delay" },
    "Shade": { "category": "Effect", "subcategory": "EQ" },
    "Thorus": { "category": "Effect", "subcategory": "Modulation" }
  },
  "Unfiltered Audio": {
    "Bass Mint": { "category": "Effect", "subcategory": "Utility" },
    "Byome": { "category": "Effect", "subcategory": "Multi-Effect" },
    "Dent 2": { "category": "Effect", "subcategory": "Distortion" },
    "Fault": { "category": "Effect", "subcategory": "Creative" },
    "G8": { "category": "Effect", "subcategory": "Dynamics" },
    "Indent 2": { "category": "Effect", "subcategory": "Dynamics" },
    "Sandman Pro": { "category": "Effect", "subcategory": "Delay" },
    "Sandman": { "category": "Effect", "subcategory": "Delay" },
    "SpecOps": { "category": "Effect", "subcategory": "Creative" },
    "Triad": { "category": "Effect", "subcategory": "EQ" },
    "Zip": { "category": "Effect", "subcategory": "Dynamics" }
  },
  "UnitedPlugins": {
    "Bassment": { "category": "Effect", "subcategory": "Utility" },
    "BassmentCore": { "category": "Effect", "subcategory": "Utility" },
    "Electrum": { "category": "Effect", "subcategory": "Distortion" },
    "ElectrumCore": { "category": "Effect", "subcategory": "Distortion" },
    "Expanse3D": { "category": "Effect", "subcategory": "Imaging" },
    "FireCharger": { "category": "Effect", "subcategory": "Distortion" },
    "FireMaster": { "category": "Effect", "subcategory": "Multi-Effect" },
    "FirePresser": { "category": "Effect", "subcategory": "Dynamics" },
    "FrontDAW": { "category": "Effect", "subcategory": "Multi-Effect" },
    "MasterMind": { "category": "Effect", "subcategory": "Multi-Effect" },
    "Mirror": { "category": "Effect", "subcategory": "Imaging" },
    "Nanopulse": { "category": "Effect", "subcategory": "Dynamics" },
    "QuickBass": { "category": "Effect", "subcategory": "Utility" },
    "QuickMuse": { "category": "Effect", "subcategory": "Creative" },
    "Retronaut": { "category": "Effect", "subcategory": "Distortion" },
    "SubbassDoctor808": { "category": "Effect", "subcategory": "Utility" },
    "Transmutator": { "category": "Effect", "subcategory": "Creative" },
    "TrapTune": { "category": "Effect", "subcategory": "Pitch" },
    "UrbanPuncher": { "category": "Effect", "subcategory": "Dynamics" },
    "VoxDucker": { "category": "Effect", "subcategory": "Dynamics" },
    "Voxessor": { "category": "Effect", "subcategory": "Multi-Effect" }
  },
  "Venomode": {
    "Pivot": { "category": "Effect", "subcategory": "EQ" }
  },
  "Voxengo": {
    "Beeper": { "category": "Effect", "subcategory": "Utility" }
  },
  "W. A. Production": {
    "Obsidian": { "category": "Effect", "subcategory": "Creative" },
    "CHORDS": { "category": "MIDI", "subcategory": null },
    "CHORDSPro": { "category": "MIDI", "subcategory": null },
    "CHORDSPro+NOTES": { "category": "MIDI", "subcategory": null },
    "ChromaBox": { "category": "Effect", "subcategory": "Distortion" },
    "Deres": { "category": "Effect", "subcategory": "Distortion" },
    "DJFX": { "category": "Effect", "subcategory": "Creative" },
    "Drifter": { "category": "Effect", "subcategory": "Modulation" },
    "Dynawide": { "category": "Effect", "subcategory": "Imaging" },
    "Ignition": { "category": "Effect", "subcategory": "Creative" },
    "Instachord 2": { "category": "MIDI", "subcategory": null },
    "ListenerLoopEngine3": { "category": "MIDI", "subcategory": null },
    "LoopEngine3": { "category": "MIDI", "subcategory": null },
    "MIDIQ": { "category": "MIDI", "subcategory": null },
    "NeonGlow": { "category": "Effect", "subcategory": "Distortion" },
    "Noizzer": { "category": "Effect", "subcategory": "Creative" },
    "RedClip": { "category": "Effect", "subcategory": "Distortion" },
    "Spectron": { "category": "Effect", "subcategory": "Creative" },
    "SphereDelay2": { "category": "Effect", "subcategory": "Delay" },
    "VocalShaper": { "category": "Effect", "subcategory": "Multi-Effect" }
  },
  "Wavesfactory": {
    "Re-Esser": { "category": "Effect", "subcategory": "Dynamics" },
    "SK10": { "category": "Effect", "subcategory": "Utility" },
    "SnareBuzz": { "category": "Effect", "subcategory": "Creative" }
  },
  "XLN Audio": {
    "Life DAW Recorder": { "category": "Effect", "subcategory": "Utility" }
  },
  "Xfer Records": {
    "Serum2": { "category": "Instrument", "subcategory": "Synth" }
  },
  "oeksound": {
    "soothe2": { "category": "Effect", "subcategory": "EQ" }
  },
  "Waves": {
    "API-2500": { "category": "Effect", "subcategory": "Dynamics" },
    "API-550": { "category": "Effect", "subcategory": "EQ" },
    "API-560": { "category": "Effect", "subcategory": "EQ" },
    "AR TG Meter Bridge": { "category": "Effect", "subcategory": "Utility" },
    "ARPlates": { "category": "Effect", "subcategory": "Reverb" },
    "Abbey Road Chambers": { "category": "Effect", "subcategory": "Reverb" },
    "Abbey Road RS124": { "category": "Effect", "subcategory": "Dynamics" },
    "Abbey Road Studio 3": { "category": "Effect", "subcategory": "Utility" },
    "Abbey Road TG Mastering Chain": { "category": "Effect", "subcategory": "Multi-Effect" },
    "Abbey Road Vinyl": { "category": "Effect", "subcategory": "Distortion" },
    "Aphex AX": { "category": "Effect", "subcategory": "Distortion" },
    "AudioTrack": { "category": "Effect", "subcategory": "Multi-Effect" },
    "B360": { "category": "Effect", "subcategory": "Utility" },
    "BB Tubes": { "category": "Effect", "subcategory": "Distortion" },
    "Bass Fingers": { "category": "Instrument", "subcategory": "Bass" },
    "Bass Rider": { "category": "Effect", "subcategory": "Dynamics" },
    "Bass Slapper": { "category": "Instrument", "subcategory": "Bass" },
    "Brauer Motion": { "category": "Effect", "subcategory": "Modulation" },
    "Butch Vig Vocals": { "category": "Effect", "subcategory": "Multi-Effect" },
    "C1": { "category": "Effect", "subcategory": "Dynamics" },
    "C360": { "category": "Effect", "subcategory": "Dynamics" },
    "C4": { "category": "Effect", "subcategory": "Dynamics" },
    "C6": { "category": "Effect", "subcategory": "Dynamics" },
    "CLA Bass": { "category": "Effect", "subcategory": "Multi-Effect" },
    "CLA Drums": { "category": "Effect", "subcategory": "Multi-Effect" },
    "CLA Effects": { "category": "Effect", "subcategory": "Multi-Effect" },
    "CLA Epic": { "category": "Effect", "subcategory": "Multi-Effect" },
    "CLA Guitars": { "category": "Effect", "subcategory": "Multi-Effect" },
    "CLA MixDown": { "category": "Effect", "subcategory": "Multi-Effect" },
    "CLA MixHub": { "category": "Effect", "subcategory": "Multi-Effect" },
    "CLA Nx": { "category": "Effect", "subcategory": "Utility" },
    "CLA Unplugged": { "category": "Effect", "subcategory": "Multi-Effect" },
    "CLA Vocals": { "category": "Effect", "subcategory": "Multi-Effect" },
    "CLA-2A": { "category": "Effect", "subcategory": "Dynamics" },
    "CLA-3A": { "category": "Effect", "subcategory": "Dynamics" },
    "CLA-76": { "category": "Effect", "subcategory": "Dynamics" },
    "CODEX": { "category": "Instrument", "subcategory": "Synth" },
    "COSMOS": { "category": "Application", "subcategory": "Application" },
    "Center": { "category": "Effect", "subcategory": "Imaging" },
    "Clarity Vx Pro": { "category": "Effect", "subcategory": "Utility" },
    "Clarity Vx": { "category": "Effect", "subcategory": "Utility" },
    "Curves AQ": { "category": "Effect", "subcategory": "EQ" },
    "Curves Equator": { "category": "Effect", "subcategory": "EQ" },
    "DPR-402": { "category": "Effect", "subcategory": "Dynamics" },
    "DeBreath": { "category": "Effect", "subcategory": "Utility" },
    "Doppler": { "category": "Effect", "subcategory": "Modulation" },
    "Dorrough Surround 5.0": { "category": "Effect", "subcategory": "Utility" },
    "Dorrough Surround 5.1": { "category": "Effect", "subcategory": "Utility" },
    "Dorrough": { "category": "Effect", "subcategory": "Utility" },
    "Doubler": { "category": "Effect", "subcategory": "Modulation" },
    "EMO-D5": { "category": "Effect", "subcategory": "Dynamics" },
    "EMO-F2": { "category": "Effect", "subcategory": "EQ" },
    "EddieKramer BA": { "category": "Effect", "subcategory": "Multi-Effect" },
    "EddieKramer DR": { "category": "Effect", "subcategory": "Multi-Effect" },
    "EddieKramer FX": { "category": "Effect", "subcategory": "Multi-Effect" },
    "EddieKramer GT": { "category": "Effect", "subcategory": "Multi-Effect" },
    "EddieKramer VC": { "category": "Effect", "subcategory": "Multi-Effect" },
    "Electric Grand 80": { "category": "Instrument", "subcategory": "Keys" },
    "Electric200": { "category": "Instrument", "subcategory": "Keys" },
    "Electric88": { "category": "Instrument", "subcategory": "Keys" },
    "Element2": { "category": "Instrument", "subcategory": "Synth" },
    "Enigma": { "category": "Effect", "subcategory": "Creative" },
    "F6": { "category": "Effect", "subcategory": "EQ" },
    "Feedback Hunter": { "category": "Effect", "subcategory": "Utility" },
    "Flow Motion": { "category": "Instrument", "subcategory": "Synth" },
    "GEQ": { "category": "Effect", "subcategory": "EQ" },
    "GTRAmp": { "category": "Effect", "subcategory": "Distortion" },
    "GTRSoloToolRack": { "category": "Effect", "subcategory": "Multi-Effect" },
    "GTRStomp": { "category": "Effect", "subcategory": "Multi-Effect" },
    "GTRToolRack": { "category": "Effect", "subcategory": "Multi-Effect" },
    "GTRTuner": { "category": "Effect", "subcategory": "Utility" },
    "Gemstones": { "category": "Effect", "subcategory": "Creative" },
    "GrandRhapsody": { "category": "Instrument", "subcategory": "Keys" },
    "Greg Wells MixCentric": { "category": "Effect", "subcategory": "Multi-Effect" },
    "Greg Wells ToneCentric": { "category": "Effect", "subcategory": "Distortion" },
    "Greg Wells VoiceCentric": { "category": "Effect", "subcategory": "Multi-Effect" },
    "Harmony": { "category": "Effect", "subcategory": "Pitch" },
    "IDX Intelligent Dynamics": { "category": "Effect", "subcategory": "Dynamics" },
    "IMPusher": { "category": "Effect", "subcategory": "Dynamics" },
    "IR-1": { "category": "Effect", "subcategory": "Reverb" },
    "IR-360": { "category": "Effect", "subcategory": "Reverb" },
    "IR-L": { "category": "Effect", "subcategory": "Reverb" },
    "IRLive": { "category": "Effect", "subcategory": "Reverb" },
    "Immersive Wrapper": { "category": "Effect", "subcategory": "Utility" },
    "InPhase LT": { "category": "Effect", "subcategory": "Utility" },
    "InPhase": { "category": "Effect", "subcategory": "Utility" },
    "J37": { "category": "Effect", "subcategory": "Distortion" },
    "JJP-Bass": { "category": "Effect", "subcategory": "Multi-Effect" },
    "JJP-Cymb-Perc": { "category": "Effect", "subcategory": "Multi-Effect" },
    "JJP-Drums": { "category": "Effect", "subcategory": "Multi-Effect" },
    "JJP-Guitars": { "category": "Effect", "subcategory": "Multi-Effect" },
    "JJP-Vocals": { "category": "Effect", "subcategory": "Multi-Effect" },
    "Kaleidoscopes": { "category": "Effect", "subcategory": "Modulation" },
    "Key Detector": { "category": "Effect", "subcategory": "Utility" },
    "KingsMic": { "category": "Effect", "subcategory": "EQ" },
    "KramerHLS": { "category": "Effect", "subcategory": "Multi-Effect" },
    "KramerPIE": { "category": "Effect", "subcategory": "Dynamics" },
    "KramerTape": { "category": "Effect", "subcategory": "Distortion" },
    "L1": { "category": "Effect", "subcategory": "Dynamics" },
    "L2": { "category": "Effect", "subcategory": "Dynamics" },
    "L3 Multi": { "category": "Effect", "subcategory": "Dynamics" },
    "L3 Ultra": { "category": "Effect", "subcategory": "Dynamics" },
    "L3-16": { "category": "Effect", "subcategory": "Dynamics" },
    "L3-LL Multi": { "category": "Effect", "subcategory": "Dynamics" },
    "L3-LL Ultra": { "category": "Effect", "subcategory": "Dynamics" },
    "L360": { "category": "Effect", "subcategory": "Dynamics" },
    "LFE360": { "category": "Effect", "subcategory": "EQ" },
    "Lil Tube": { "category": "Effect", "subcategory": "Distortion" },
    "LinMB": { "category": "Effect", "subcategory": "Dynamics" },
    "LoAir": { "category": "Effect", "subcategory": "Utility" },
    "MIDIArpSeq": { "category": "MIDI", "subcategory": null },
    "MIDIChords": { "category": "MIDI", "subcategory": null },
    "MIDIKeyboard": { "category": "MIDI", "subcategory": null },
    "MIDIMonitor": { "category": "MIDI", "subcategory": null },
    "MIDIRange": { "category": "MIDI", "subcategory": null },
    "MIDITranspose": { "category": "MIDI", "subcategory": null },
    "MIDIVelocity": { "category": "MIDI", "subcategory": null },
    "MIDIVoicing": { "category": "MIDI", "subcategory": null },
    "MV2": { "category": "Effect", "subcategory": "Dynamics" },
    "MV360": { "category": "Effect", "subcategory": "Dynamics" },
    "MagmaSprings": { "category": "Effect", "subcategory": "Reverb" },
    "MannyM-ToneShaper": { "category": "Effect", "subcategory": "Multi-Effect" },
    "MannyM-TripleD": { "category": "Effect", "subcategory": "Dynamics" },
    "Maserati ACG": { "category": "Effect", "subcategory": "Multi-Effect" },
    "Maserati B72": { "category": "Effect", "subcategory": "Multi-Effect" },
    "Maserati DRM": { "category": "Effect", "subcategory": "Multi-Effect" },
    "Maserati GRP": { "category": "Effect", "subcategory": "Multi-Effect" },
    "Maserati GTi": { "category": "Effect", "subcategory": "Multi-Effect" },
    "Maserati HMX": { "category": "Effect", "subcategory": "Multi-Effect" },
    "Maserati VX1": { "category": "Effect", "subcategory": "Multi-Effect" },
    "MaxxBass": { "category": "Effect", "subcategory": "Utility" },
    "MaxxVolume": { "category": "Effect", "subcategory": "Dynamics" },
    "ModFX_Autopan": { "category": "Effect", "subcategory": "Modulation" },
    "ModFX_Chorus": { "category": "Effect", "subcategory": "Modulation" },
    "ModFX_Compressor": { "category": "Effect", "subcategory": "Dynamics" },
    "ModFX_Delay": { "category": "Effect", "subcategory": "Delay" },
    "ModFX_Distortion": { "category": "Effect", "subcategory": "Distortion" },
    "ModFX_Limiter": { "category": "Effect", "subcategory": "Dynamics" },
    "ModFX_Reverb": { "category": "Effect", "subcategory": "Reverb" },
    "MondoMod": { "category": "Effect", "subcategory": "Modulation" },
    "Morphoder": { "category": "Effect", "subcategory": "Pitch" },
    "MultiMod Rack": { "category": "Effect", "subcategory": "Modulation" },
    "NLS": { "category": "Effect", "subcategory": "Distortion" },
    "NS1": { "category": "Effect", "subcategory": "Utility" },
    "NX": { "category": "Effect", "subcategory": "Utility" },
    "Nx Germano Studios": { "category": "Effect", "subcategory": "Utility" },
    "Nx Ocean Way Nashville": { "category": "Effect", "subcategory": "Utility" },
    "OKBrighter": { "category": "Effect", "subcategory": "EQ" },
    "OKDriver": { "category": "Effect", "subcategory": "Distortion" },
    "OKLouder": { "category": "Effect", "subcategory": "Dynamics" },
    "OKPhatter": { "category": "Effect", "subcategory": "EQ" },
    "OKPressure": { "category": "Effect", "subcategory": "Dynamics" },
    "OKPumper": { "category": "Effect", "subcategory": "Dynamics" },
    "OKWetter": { "category": "Effect", "subcategory": "Reverb" },
    "OVox": { "category": "Effect", "subcategory": "Pitch" },
    "PAZ": { "category": "Effect", "subcategory": "Utility" },
    "PRS Supermodels": { "category": "Effect", "subcategory": "Distortion" },
    "PS22": { "category": "Effect", "subcategory": "Imaging" },
    "PlaylistRider": { "category": "Effect", "subcategory": "Dynamics" },
    "PuigChild": { "category": "Effect", "subcategory": "Dynamics" },
    "PuigTec": { "category": "Effect", "subcategory": "EQ" },
    "Q-Clone": { "category": "Effect", "subcategory": "EQ" },
    "Q10": { "category": "Effect", "subcategory": "EQ" },
    "R360": { "category": "Effect", "subcategory": "Reverb" },
    "RBass": { "category": "Effect", "subcategory": "Utility" },
    "RChannel": { "category": "Effect", "subcategory": "Multi-Effect" },
    "REDD17": { "category": "Effect", "subcategory": "Distortion" },
    "REDD37-51": { "category": "Effect", "subcategory": "Distortion" },
    "REQ": { "category": "Effect", "subcategory": "EQ" },
    "RS56": { "category": "Effect", "subcategory": "EQ" },
    "RVox": { "category": "Effect", "subcategory": "Dynamics" },
    "Reel ADT": { "category": "Effect", "subcategory": "Modulation" },
    "RenAxx": { "category": "Effect", "subcategory": "Dynamics" },
    "Retro Fi": { "category": "Effect", "subcategory": "Distortion" },
    "S1": { "category": "Effect", "subcategory": "Imaging" },
    "S360": { "category": "Effect", "subcategory": "Imaging" },
    "SSLEQ": { "category": "Effect", "subcategory": "EQ" },
    "Saphira": { "category": "Effect", "subcategory": "Distortion" },
    "Scheps 73": { "category": "Effect", "subcategory": "EQ" },
    "Scheps Parallel Particles": { "category": "Effect", "subcategory": "Distortion" },
    "Sibilance": { "category": "Effect", "subcategory": "Dynamics" },
    "Silk Vocal": { "category": "Effect", "subcategory": "Multi-Effect" },
    "Smack Attack": { "category": "Effect", "subcategory": "Dynamics" },
    "SoundShifter": { "category": "Effect", "subcategory": "Pitch" },
    "StompAxxPress": { "category": "Effect", "subcategory": "Dynamics" },
    "StompBuzz": { "category": "Effect", "subcategory": "Distortion" },
    "StompDoubler": { "category": "Effect", "subcategory": "Modulation" },
    "StompLayD": { "category": "Effect", "subcategory": "Delay" },
    "StompMetal": { "category": "Effect", "subcategory": "Distortion" },
    "StompOctaver": { "category": "Effect", "subcategory": "Pitch" },
    "StompOverDrive": { "category": "Effect", "subcategory": "Distortion" },
    "StompPanner": { "category": "Effect", "subcategory": "Modulation" },
    "StompPitcher": { "category": "Effect", "subcategory": "Pitch" },
    "StompSLEQ": { "category": "Effect", "subcategory": "EQ" },
    "StompSLOverDrive": { "category": "Effect", "subcategory": "Distortion" },
    "StompSLPitcher": { "category": "Effect", "subcategory": "Pitch" },
    "StompSLVibrolo": { "category": "Effect", "subcategory": "Modulation" },
    "StompSLVolume": { "category": "Effect", "subcategory": "Utility" },
    "StompSLWahWah": { "category": "Effect", "subcategory": "EQ" },
    "StompTone": { "category": "Effect", "subcategory": "EQ" },
    "StompVibrolo": { "category": "Effect", "subcategory": "Modulation" },
    "StompVolume": { "category": "Effect", "subcategory": "Utility" },
    "StompWahWah": { "category": "Effect", "subcategory": "EQ" },
    "StudioRack for OBS": { "category": "Effect", "subcategory": "Utility" },
    "StudioVerse Audio Effects": { "category": "Effect", "subcategory": "Multi-Effect" },
    "StudioVerse Instruments": { "category": "Instrument", "subcategory": "Synth" },
    "Sub Align": { "category": "Effect", "subcategory": "Utility" },
    "Submarine": { "category": "Effect", "subcategory": "Utility" },
    "SuperTap": { "category": "Effect", "subcategory": "Delay" },
    "TG12345": { "category": "Effect", "subcategory": "Multi-Effect" },
    "TRACT": { "category": "Effect", "subcategory": "Utility" },
    "Torque": { "category": "Effect", "subcategory": "Pitch" },
    "TransX": { "category": "Effect", "subcategory": "Dynamics" },
    "Tune Real-Time": { "category": "Effect", "subcategory": "Pitch" },
    "UltraPitch": { "category": "Effect", "subcategory": "Pitch" },
    "VEQ3": { "category": "Effect", "subcategory": "EQ" },
    "VEQ4": { "category": "Effect", "subcategory": "EQ" },
    "Vitamin": { "category": "Effect", "subcategory": "Distortion" },
    "Vocal Bender": { "category": "Effect", "subcategory": "Pitch" },
    "Vocal Rider": { "category": "Effect", "subcategory": "Dynamics" },
    "Voltage Amps Bass": { "category": "Effect", "subcategory": "Distortion" },
    "Voltage Amps Guitar": { "category": "Effect", "subcategory": "Distortion" },
    "W43": { "category": "Effect", "subcategory": "Utility" },
    "WLM Plus": { "category": "Effect", "subcategory": "Utility" },
    "WLM": { "category": "Effect", "subcategory": "Utility" },
    "WNS": { "category": "Effect", "subcategory": "Utility" },
    "WavesTune LT": { "category": "Effect", "subcategory": "Pitch" },
    "WavesTune": { "category": "Effect", "subcategory": "Pitch" },
    "X-Click": { "category": "Effect", "subcategory": "Utility" },
    "X-Crackle": { "category": "Effect", "subcategory": "Utility" },
    "X-FDBK": { "category": "Effect", "subcategory": "Utility" },
    "X-Hum": { "category": "Effect", "subcategory": "Utility" },
    "X-Noise": { "category": "Effect", "subcategory": "Utility" },
    "Z-Noise": { "category": "Effect", "subcategory": "Utility" },
    "dbx-160": { "category": "Effect", "subcategory": "Dynamics" }
  }
}
